{
    "liabInfos": [
        {
            "categoryId": 261,
            "categoryName": "Death",
            "claimTypes": [
                {
                    "claimType": 355,
                    "typeCode": "1",
                    "typeDesc": "Accident"
                },
                {
                    "claimType": 356,
                    "typeCode": "2",
                    "typeDesc": "Death"
                },
                {
                    "claimType": 357,
                    "typeCode": "9",
                    "typeDesc": "Others"
                },
                {
                    "claimType": 362,
                    "typeCode": "11",
                    "typeDesc": "Premium Waiver Rider due to Disability"
                },
                {
                    "claimType": 484,
                    "typeCode": "5",
                    "typeDesc": "Hospitalisation"
                }
            ],
            "extendedProps": {},
            "isPricedOnLiab": "N",
            "liabilityCode": "1001",
            "liabilityId": 78113588,
            "liabilityName": "Death",
            "optionalIndi": "N"
        },
        {
            "categoryId": 262,
            "categoryName": "TPD",
            "claimTypes": [
                {
                    "claimType": 356,
                    "typeCode": "2",
                    "typeDesc": "Death"
                },
                {
                    "claimType": 357,
                    "typeCode": "9",
                    "typeDesc": "Others"
                },
                {
                    "claimType": 358,
                    "typeCode": "12",
                    "typeDesc": "Total and Permanent Disability"
                },
                {
                    "claimType": 484,
                    "typeCode": "5",
                    "typeDesc": "Hospitalisation"
                },
                {
                    "claimType": 485,
                    "typeCode": "13",
                    "typeDesc": "TPD keep TIV"
                }
            ],
            "extendedProps": {},
            "isPricedOnLiab": "N",
            "liabilityCode": "2001",
            "liabilityId": 78113589,
            "liabilityName": "Total & Permanent Disability",
            "optionalIndi": "N"
        }
    ],
    "premiumFrequencys": [
        "4",
        "5"
    ],
    "product": {
        "advanProgram": "N",
        "ageBase": "1",
        "ageLimits": [
            {
                "areaCode": "0",
                "benefitLevel": "0",
                "benefitOption": "0",
                "chargePeriod": "0",
                "chargeType": "0",
                "chargeYear": 0,
                "chargeYearMax": 9999,
                "coveragePeriod": "0",
                "coverageYear": 0,
                "coverageYearMax": 9999,
                "empty": false,
                "endPeriod": "0",
                "endYear": 0,
                "endYearMax": 9999,
                "entityId": 86449386,
                "extendedFactors": {},
                "extendedResults": {},
                "gender": "N",
                "highSa": 9999999999999999,
                "insertTime": "2024-08-16T18:01:36.000+0800",
                "insuredStatus": "0",
                "listId": 86449386,
                "lowSa": 0,
                "maxDefermentAge": 999,
                "maxInsdNbAge": 55,
                "maxInsdNbAgeUnit": "1",
                "maxInsdNbExAge": 999,
                "maxInsdNbPuAge": 66,
                "maxInsdRnAge": 65,
                "maxInsdRnExAge": 66,
                "maxJiNbAge": 999,
                "maxJiNbAgeUnit": "1",
                "maxPhNbAge": 999,
                "maxSaFactor": 999999,
                "minDefermentAge": 0,
                "minInsdNbAge": 18,
                "minInsdNbAgeUnit": "1",
                "minInsdNbExAge": 19,
                "minInvestPeriod": 0,
                "minJiNbAge": 0,
                "minJiNbAgeUnit": "1",
                "minPhNbAge": 18,
                "minSaFactor": 0,
                "payEnsure": 0,
                "payMode": 0,
                "payPeriod": "0",
                "payYear": 0,
                "payYearMax": 9999,
                "productId": 4005461,
                "productVersionId": 86446974,
                "recorderId": 401,
                "specialAuth": 0,
                "updateTime": "2024-08-16T18:01:36.000+0800",
                "updaterId": 401
            }
        ],
        "ageMethod": "2",
        "ally": "0",
        "apilpIndi": "N",
        "apilpK": 0,
        "assetShare": "N",
        "attachable": "N",
        "aurpSpecificTerms": "N",
        "autoBackdateIndi": "N",
        "backdateIndi": "N",
        "backdatePeriod": 999,
        "backdateUnit": "1",
        "baseMoney": 4,
        "benefitFreqIndi": "0",
        "benefitType": "14",
        "bereavementIndi": "N",
        "bonusCalType": "D",
        "bonusVestYearClm": 0,
        "bonusVestYearSurr": 0,
        "bucketFillingOption": "0",
        "cashBonusIndi": "N",
        "cashbackRiderIndi": "N",
        "cbVestYear": 0,
        "checkAmount": 9999999999999999,
        "checked": "N",
        "commAmount": "N",
        "commStartDdIndi": "N",
        "conversionPriv": "N",
        "coverageExtendIndi": "Y",
        "dbBaseClm": 0,
        "deferPeriod": "N",
        "dieOption": 1,
        "doppIndi": "N",
        "editable": "Y",
        "em": 0,
        "empty": false,
        "entityId": 4005461,
        "familyType": "0",
        "fatcaCrsIndi": "N",
        "featureDesc": "Regular Premium Term Product (one years renewable) with Death, Critical Illnesses Benefit7",
        "finProdIndicator": "0",
        "firstOfMonth": "N",
        "flexiblePeriod": 0,
        "followCommision": "N",
        "followDiscnt": "N",
        "followMpv": "N",
        "formulaDriven": "N",
        "freeSwitchTimes": 0,
        "freeWitdrTimes": 1,
        "fullDeclare": "N",
        "fullPrepayment": "N",
        "gbExpiryAgeIndi": "N",
        "gbFactorIndi": "N",
        "gjaIndi": "N",
        "gscIndi": "N",
        "gstIndicator": "0",
        "gsvVestYear": 0,
        "gurntPeriod": 0,
        "gurntPeriodType": "1",
        "gurntPeriodUnit": "1",
        "hasFlexiblePeriod": "N",
        "hiPolFeeIndi": "N",
        "hthFullDeclare": "N",
        "hybridIndi": "N",
        "illRate": 0,
        "incrPremPermit": "N",
        "individualGroup": "1",
        "indxIndi": "N",
        "indxYear": 0,
        "initialId": "1YearRenewabTerm",
        "insType": "1",
        "insureMonth": "N",
        "internalId": "1YearRenewabTerm",
        "investCashRiderIndi": "N",
        "investDelay": 0,
        "isNetInvest": "N",
        "laChange": "N",
        "ladrIndi": "N",
        "lapseMethod": 1,
        "liabPayParams": [
            {
                "bscPayFormula": "DIPLI_000000001013407",
                "coverage": 0,
                "empty": false,
                "entityId": 86449395,
                "formulaDriven": "Y",
                "generatedEntityId": 86449395,
                "insertTime": "2024-08-16T18:01:37.000+0800",
                "liabId": 78113588,
                "listId": 86449395,
                "param1": 1,
                "param1Desc": "",
                "param2Desc": "",
                "productId": 4005461,
                "productVersionId": 86446974,
                "recorderId": 401,
                "updateTime": "2024-08-16T18:01:37.000+0800",
                "updaterId": 401
            },
            {
                "bscPayFormula": "DIPLI_000000001013407",
                "coverage": 0,
                "empty": false,
                "entityId": 86449396,
                "formulaDriven": "Y",
                "generatedEntityId": 86449396,
                "insertTime": "2024-08-16T18:01:37.000+0800",
                "liabId": 78113589,
                "listId": 86449396,
                "param1": 1,
                "productId": 4005461,
                "productVersionId": 86446974,
                "recorderId": 401,
                "relv1Value": "",
                "relv2Value": "",
                "relv3Value": "",
                "relv4Value": "",
                "relv5Value": "",
                "relv6Value": "",
                "updateTime": "2024-08-16T18:01:37.000+0800",
                "updaterId": 401
            }
        ],
        "liabPayRelatives": [
            {
                "empty": false,
                "entityId": 86449397,
                "insertTime": "2024-08-16T18:01:37.000+0800",
                "isPricedOnLiab": "N",
                "liabId": 78113588,
                "listId": 86449397,
                "optionalIndi": "N",
                "productId": 4005461,
                "productVersionId": 86446974,
                "recorderId": 401,
                "updateTime": "2024-08-16T18:01:37.000+0800",
                "updaterId": 401
            },
            {
                "empty": false,
                "entityId": 86449398,
                "insertTime": "2024-08-16T18:01:37.000+0800",
                "isPricedOnLiab": "N",
                "liabId": 78113589,
                "listId": 86449398,
                "optionalIndi": "N",
                "productId": 4005461,
                "productVersionId": 86446974,
                "recorderId": 401,
                "updateTime": "2024-08-16T18:01:37.000+0800",
                "updaterId": 401
            }
        ],
        "lifeBasics": [
            {
                "basicCode": "0",
                "basicId": 86449388,
                "chargePeriod": "5",
                "chargeYear": 4,
                "coveragePeriod": "2",
                "coverageYear": 1,
                "empty": false,
                "endPeriod": "0",
                "endYear": 0,
                "entityId": 86449388,
                "extendedFactors": {},
                "extendedResults": {},
                "increaseFreq": "0",
                "increaseRate": 0,
                "increaseYear": 0,
                "insertTime": "2024-08-16T18:01:36.000+0800",
                "maxInsuredAge": 999,
                "maxInsuredRenew": 999,
                "maxSaFactor": 999999,
                "minInsuredAge": 0,
                "minSaFactor": 0,
                "payEnsure": 999,
                "payPeriod": "0",
                "payYear": 0,
                "productId": 4005461,
                "productVersionId": 86446974,
                "recorderId": 401,
                "simpleCompound": "0",
                "updateTime": "2024-08-16T18:01:36.000+0800",
                "updaterId": 401,
                "withdrawEndPeriod": "0",
                "withdrawEndYear": 0,
                "withdrawStartPeriod": "0",
                "withdrawStartYear": 0
            },
            {
                "basicCode": "0",
                "basicId": 86449389,
                "chargePeriod": "5",
                "chargeYear": 9,
                "coveragePeriod": "2",
                "coverageYear": 1,
                "empty": false,
                "endPeriod": "0",
                "endYear": 0,
                "entityId": 86449389,
                "extendedFactors": {},
                "extendedResults": {},
                "increaseFreq": "0",
                "increaseRate": 0,
                "increaseYear": 0,
                "insertTime": "2024-08-16T18:01:36.000+0800",
                "maxInsuredAge": 999,
                "maxInsuredRenew": 999,
                "maxSaFactor": 999999,
                "minInsuredAge": 0,
                "minSaFactor": 0,
                "payEnsure": 999,
                "payPeriod": "0",
                "payYear": 0,
                "productId": 4005461,
                "productVersionId": 86446974,
                "recorderId": 401,
                "simpleCompound": "0",
                "updateTime": "2024-08-16T18:01:36.000+0800",
                "updaterId": 401,
                "withdrawEndPeriod": "0",
                "withdrawEndYear": 0,
                "withdrawStartPeriod": "0",
                "withdrawStartYear": 0
            },
            {
                "basicCode": "0",
                "basicId": 86449390,
                "chargePeriod": "5",
                "chargeYear": 12,
                "coveragePeriod": "2",
                "coverageYear": 1,
                "empty": false,
                "endPeriod": "0",
                "endYear": 0,
                "entityId": 86449390,
                "extendedFactors": {},
                "extendedResults": {},
                "increaseFreq": "0",
                "increaseRate": 0,
                "increaseYear": 0,
                "insertTime": "2024-08-16T18:01:36.000+0800",
                "maxInsuredAge": 999,
                "maxInsuredRenew": 999,
                "maxSaFactor": 999999,
                "minInsuredAge": 0,
                "minSaFactor": 0,
                "payEnsure": 999,
                "payPeriod": "0",
                "payYear": 0,
                "productId": 4005461,
                "productVersionId": 86446974,
                "recorderId": 401,
                "simpleCompound": "0",
                "updateTime": "2024-08-16T18:01:36.000+0800",
                "updaterId": 401,
                "withdrawEndPeriod": "0",
                "withdrawEndYear": 0,
                "withdrawStartPeriod": "0",
                "withdrawStartYear": 0
            },
            {
                "basicCode": "0",
                "basicId": 86449391,
                "chargePeriod": "1",
                "chargeYear": 0,
                "coveragePeriod": "2",
                "coverageYear": 1,
                "empty": false,
                "endPeriod": "0",
                "endYear": 0,
                "entityId": 86449391,
                "extendedFactors": {},
                "extendedResults": {},
                "increaseFreq": "0",
                "increaseRate": 0,
                "increaseYear": 0,
                "insertTime": "2024-08-16T18:01:36.000+0800",
                "maxInsuredAge": 999,
                "maxInsuredRenew": 999,
                "maxSaFactor": 999999,
                "minInsuredAge": 0,
                "minSaFactor": 0,
                "payEnsure": 999,
                "payPeriod": "0",
                "payYear": 0,
                "productId": 4005461,
                "productVersionId": 86446974,
                "recorderId": 401,
                "simpleCompound": "0",
                "updateTime": "2024-08-16T18:01:36.000+0800",
                "updaterId": 401,
                "withdrawEndPeriod": "0",
                "withdrawEndYear": 0,
                "withdrawStartPeriod": "0",
                "withdrawStartYear": 0
            }
        ],
        "lifeRate": 0,
        "lockInPeriod": 0,
        "lockInPeriodOption": 0,
        "maxCompCommi": 0,
        "maxDeferPeriod": 99,
        "maxSurValue": 9999999999999999,
        "maxSwitInTimes": 0,
        "maxSwitOutTimes": 0,
        "maxSwitchTimes": 0,
        "maxWaivPremAnn": 9999999999999999,
        "minClaimAmount": 0,
        "minDeferPeriod": 0,
        "minRemainValue": 0,
        "minSurValue": 0,
        "modelFactorRateAn": 1,
        "mortagage": "N",
        "nbBeforeExpiryAgeIndi": "N",
        "noClaimDiscnt": "N",
        "nonLapPeriod": 0,
        "nonLapPeriodFollowMip": "N",
        "orgId": 71964568,
        "parNonIlp": "0",
        "partialWithdraw": "N",
        "partialWithdrawStartYear": 1,
        "payerWop": "N",
        "periodCalType": "1",
        "periodType": "0",
        "persAnnuTaxTerm": "N",
        "phLaRelation": 1,
        "phdRateCate": "0",
        "pldGracePeriod": 0,
        "policyHolderWaiver": "N",
        "policySection": "0",
        "postdateIndi": "N",
        "pregnantInsured": "Y",
        "premChangeNotice": "N",
        "premTable": "1",
        "premiumDefine": "0",
        "prepaymentIndi": "N",
        "productAbbr": "1YearRenewabTerm",
        "productAggrRisks": [
            {
                "aggrRate": 1,
                "aggrRiskType": 9,
                "empty": false,
                "entityId": 86449385,
                "factorId": "DIPLI_000000001014027",
                "listId": 86449385,
                "productId": 4005461,
                "productVersionId": 86446974
            }
        ],
        "productCsRules": [
            {
                "addAllowPolicyYear": 999,
                "addPermit": "Y",
                "adminCharge": 0,
                "annuitySurrFac": 0,
                "aplPermit": "N",
                "assignmentIndi": "N",
                "autoEta": "N",
                "autoPhd": "N",
                "autoReducePaidup": "N",
                "autoReinstatementIndi": "N",
                "autoReinstatementPeriod": 0,
                "autoSurrender": "N",
                "bonusEncash": "N",
                "changeInsuredPermit": "N",
                "decreaseAllowPolicyYear": 999,
                "decreasePermit": "Y",
                "deductedFromTiv": "N",
                "empty": false,
                "entityId": 86449399,
                "etaPermit": "N",
                "forceLapseIndi": "N",
                "freeLookFollow": "N",
                "freeLookIndi": "Y",
                "freeLookPeriod": 14,
                "graceFollow": "N",
                "gracePeriod": 30,
                "gracePeriodAdd": 15,
                "listId": 86449399,
                "loanPermit": "N",
                "maxLoanRate": 0.92,
                "maxReinsPeriUnit": "4",
                "maxReinsPeriod": 6,
                "minAddAmount": 0,
                "minAddUnits": 0,
                "minSurAmount": 0,
                "minSurUnits": 0,
                "overdueIntIndi": "N",
                "permitPrs": "N",
                "phdPerformOption": "1",
                "preferLifeIndi": "N",
                "premVouchPermit": "N",
                "premVouchRate": 0,
                "productId": 4005461,
                "productVersionId": 86446974,
                "reducePaidup": "N",
                "renew": "Y",
                "specialRevivalPermit": "N",
                "surrPermit": "0"
            }
        ],
        "productCurrencies": [
            {
                "empty": false,
                "entityFund": "EBAO1001",
                "entityFundType": "0",
                "insertTime": "2024-08-16T18:01:36.000+0800",
                "moneyId": 4,
                "organId": 71964568,
                "productId": 4005461,
                "recorderId": 401,
                "updateTime": "2024-08-16T18:01:36.000+0800",
                "updaterId": 401
            }
        ],
        "productFormulas": [
            {
                "empty": false,
                "entityId": 86446976,
                "formulaId": "DIPLI_000000001019510",
                "formulaTypeId": 1,
                "listId": 86446976,
                "productId": 4005461
            },
            {
                "empty": false,
                "entityId": 86446977,
                "formulaId": "DIPLI_000000001019511",
                "formulaTypeId": 26,
                "listId": 86446977,
                "productId": 4005461
            },
            {
                "empty": false,
                "entityId": 86446978,
                "formulaId": "DIPLI_000000001019512",
                "formulaTypeId": 9,
                "listId": 86446978,
                "productId": 4005461
            }
        ],
        "productId": 4005461,
        "productLifeDiff": {
            "ageMonthDiff": "N",
            "ageMonthRDiff": "N",
            "agePrem": "0",
            "amountDiff": "N",
            "amountSection": "N",
            "basicChargePeriod": "Y",
            "basicCoveragePeriod": "Y",
            "basicIncreaseYear": "N",
            "basicInsuredAge": "N",
            "basicPayEnsure": "N",
            "basicPayPeriod": "N",
            "basicPayPeriodEnd": "N",
            "basicSaFactor": "N",
            "basicWithdrawEndPeriod": "N",
            "basicWithdrawEndYear": "N",
            "basicWithdrawStartPeriod": "N",
            "basicWithdrawStartYear": "N",
            "benPeriodTypeDiff": "N",
            "benefitLevel": "N",
            "benefitPeriodDiff": "N",
            "categoryDiff": "N",
            "cbBonusCalTypeDiff": "N",
            "cbChargeDiff": "N",
            "cbDueMonthDiff": "N",
            "cbDurDiff": "N",
            "cbEntryAgeDiff": "N",
            "cbEntryAgeMonthDiff": "N",
            "cbGenderDiff": "N",
            "cbInsuredDiff": "N",
            "cbPeriodDiff": "N",
            "cbPremYearDiff": "N",
            "cbSaDiff": "N",
            "cbSmokDiff": "N",
            "cbSpDiff": "N",
            "claimCnt": "N",
            "coverageExcept": "N",
            "coveragePerPayLimit": "N",
            "dayPerPayLimit": "N",
            "empty": false,
            "entityId": 4005461,
            "exceptDiff": "N",
            "genderDiff": "N",
            "genderRDiff": "N",
            "housekeeperDiff": "N",
            "ilpChargeMode": "0",
            "ilpIssuFeeMode": "0",
            "ilpMortFeeMode": "0",
            "insuredStatusDiff": "N",
            "insuredStatusRDiff": "N",
            "isuWaivCondtn": "0",
            "isuWaivLimit": 0,
            "jobDiff": "N",
            "levelDiff": "N",
            "lifePayLimit": "N",
            "lifeTableAnnuity": "N",
            "lifeTableGender": "N",
            "lifeTableSmoking": "N",
            "liveRangeDiff": "N",
            "loanRateDiff": "N",
            "loanTypeDiff": "N",
            "monthPerPayLimit": "N",
            "moveRangeDiff": "N",
            "oncePayRate": "N",
            "oncePerPayLimit": "N",
            "payRateDiff": "N",
            "periodDiff": "N",
            "premiumSection": "N",
            "premiumYearDiff": "N",
            "productId": 4005461,
            "rbChargeDiff": "N",
            "rbDueMonthDiff": "N",
            "rbDurDiff": "N",
            "rbEntryAgeDiff": "N",
            "rbEntryAgeMonthDiff": "N",
            "rbGenderDiff": "N",
            "rbInsuredDiff": "N",
            "rbPeriodDiff": "N",
            "rbPremYearDiff": "N",
            "rbPwIndiDiff": "N",
            "rbSaDiff": "N",
            "rbSmokDiff": "N",
            "rbSpDiff": "N",
            "rbSpIndiDiff": "N",
            "retiredDiff": "N",
            "retiredRateDiff": "N",
            "smokingDiff": "N",
            "smokingRDiff": "N",
            "tbChargeDiff": "N",
            "tbDueMonthDiff": "N",
            "tbDurDiff": "N",
            "tbEntryAgeDiff": "N",
            "tbEntryAgeMonthDiff": "N",
            "tbGenderDiff": "N",
            "tbInsuredDiff": "N",
            "tbPeriodDiff": "N",
            "tbPremYearDiff": "N",
            "tbSaDiff": "N",
            "tbSmokDiff": "N",
            "tbSpDiff": "N",
            "unitsSection": "N",
            "valueAge": "0",
            "valueAgeMonth": "N",
            "valueAgeMonthR": "N",
            "valueBenStatus": "N",
            "valueCategory": "N",
            "valueChargeType": "N",
            "valueExcept": "N",
            "valueGender": "N",
            "valueGenderR": "N",
            "valueHouse": "N",
            "valueIncrease": "N",
            "valueInsuredStatus": "N",
            "valueJobCate": "N",
            "valueLevel": "N",
            "valuePayEnd": "N",
            "valuePayEnsure": "N",
            "valuePayPeriod": "N",
            "valuePayRate": "N",
            "valuePayType": "N",
            "valuePeriod": "N",
            "valuePolYear": "N",
            "valuePremiumYear": "N",
            "valueRetired": "N",
            "valueSmoking": "N",
            "valueUnitAmount": 0,
            "waitPeriodDiff": "N",
            "yearPerPayLimit": "N",
            "yieldChargeDiff": "N",
            "yieldDueMonthDiff": "N",
            "yieldDurDiff": "N",
            "yieldEntryAgeDiff": "N",
            "yieldEntryAgeMonthDiff": "N",
            "yieldGenderDiff": "N",
            "yieldInsuredDiff": "N",
            "yieldPeriodDiff": "N",
            "yieldPlanDiff": "N",
            "yieldPremYearDiff": "N",
            "yieldSaDiff": "N",
            "yieldSmokDiff": "N",
            "yieldSpDiff": "N"
        },
        "productName": "1 YEAR RENEWABLE Life InsuranceCopy",
        "productOrgs": [
            {
                "defaultMoney": 4,
                "empty": false,
                "insertTime": "2024-08-16T18:01:36.000+0800",
                "organId": 71964568,
                "productId": 4005461,
                "recorderId": 401,
                "updateTime": "2024-08-16T18:01:36.000+0800",
                "updaterId": 401
            }
        ],
        "productPayModes": [
            {
                "chargeType": "5",
                "empty": false,
                "entityId": 86449392,
                "insertTime": "2024-08-16T18:01:37.000+0800",
                "listId": 86449392,
                "moneyId": 0,
                "payMode": 1,
                "premSequen": "0",
                "prepaymentType": 0,
                "productId": 4005461,
                "productVersionId": 86446974,
                "recorderId": 401,
                "specialAuth": 0,
                "updateTime": "2024-08-16T18:01:37.000+0800",
                "updaterId": 401
            },
            {
                "chargeType": "4",
                "empty": false,
                "entityId": 86449393,
                "insertTime": "2024-08-16T18:01:37.000+0800",
                "listId": 86449393,
                "moneyId": 0,
                "payMode": 3,
                "premSequen": "0",
                "prepaymentType": 0,
                "productId": 4005461,
                "productVersionId": 86446974,
                "recorderId": 401,
                "specialAuth": 0,
                "updateTime": "2024-08-16T18:01:37.000+0800",
                "updaterId": 401
            },
            {
                "chargeType": "4",
                "empty": false,
                "entityId": 86449394,
                "insertTime": "2024-08-16T18:01:37.000+0800",
                "listId": 86449394,
                "moneyId": 0,
                "payMode": 30,
                "premSequen": "0",
                "prepaymentType": 0,
                "productId": 4005461,
                "productVersionId": 86446974,
                "recorderId": 401,
                "specialAuth": 0,
                "updateTime": "2024-08-16T18:01:37.000+0800",
                "updaterId": 401
            }
        ],
        "productRatetables": [
            {
                "empty": false,
                "entityId": 86446979,
                "insertTime": "2024-08-16T18:01:36.000+0800",
                "insertedBy": 401,
                "listId": 86446979,
                "productId": 4005461,
                "ratetableCode": "RATE_DIPLI_000000001058715",
                "ratetableType": 1,
                "updateTime": "2024-08-16T18:01:36.000+0800",
                "updatedBy": 401
            },
            {
                "empty": false,
                "entityId": 86446980,
                "insertTime": "2024-08-16T18:01:36.000+0800",
                "insertedBy": 401,
                "listId": 86446980,
                "productId": 4005461,
                "ratetableCode": "RATE_DIPLI_000000001058716",
                "ratetableType": 15,
                "updateTime": "2024-08-16T18:01:36.000+0800",
                "updatedBy": 401
            },
            {
                "empty": false,
                "entityId": 86446982,
                "insertTime": "2024-08-16T18:01:36.000+0800",
                "insertedBy": 401,
                "listId": 86446982,
                "productId": 4005461,
                "ratetableCode": "RATE_DIPLI_000000001058717",
                "ratetableType": 281,
                "updateTime": "2024-08-16T18:01:36.000+0800",
                "updatedBy": 401
            },
            {
                "empty": false,
                "entityId": 86449384,
                "insertTime": "2024-08-16T18:01:36.000+0800",
                "insertedBy": 401,
                "listId": 86449384,
                "productId": 4005461,
                "ratetableCode": "RATE_DIPLI_000000001030110",
                "ratetableType": 20,
                "updateTime": "2024-08-16T18:01:36.000+0800",
                "updatedBy": 401
            }
        ],
        "productSurvivals": [
            {
                "empty": false,
                "productId": 4005461,
                "survivalOption": "1"
            },
            {
                "empty": false,
                "productId": 4005461,
                "survivalOption": "2"
            },
            {
                "empty": false,
                "productId": 4005461,
                "survivalOption": "3"
            }
        ],
        "productVersions": [
            {
                "empty": false,
                "entityId": 86446974,
                "productId": 4005461,
                "productVersion": "1YearRenewabTerm",
                "versionDesc": "Initial Version",
                "versionId": 86446974,
                "versionStartDate": "2023-06-01T08:00:00.000+0800"
            }
        ],
        "pseudo": "N",
        "purcNewPol": "N",
        "raObject": "9",
        "receiptIndi": "N",
        "regPartWitdrPer": "N",
        "regPartWitdrStartYear": 1,
        "regPartWithdrMaxAmount": 9999999999999999,
        "regPartWithdrMinAmount": 0,
        "regTopupPermit": "N",
        "reguToSingle": "N",
        "revBonusIndi": "N",
        "riAgeBase": "1",
        "riCalcBasis": "0",
        "riFactorTableCode": "0",
        "riRenewalFreq": "1",
        "riskAggrFormula": 0,
        "rnDateType": "4",
        "saAccum": "Y",
        "saLimits": [
            {
                "declarationType": "0",
                "employedIndi": "99",
                "empty": false,
                "entityId": 86449387,
                "extendedFactors": {},
                "extendedResults": {},
                "highAgeMonth": 999,
                "insdMaxAmount": 999999999999999,
                "insdMinAmount": 10000,
                "insertTime": "2024-08-16T18:01:36.000+0800",
                "insuredStatus": "0",
                "jobCate": 0,
                "limitUnit": "1",
                "listId": 86449387,
                "lowAgeMonth": 0,
                "moneyId": 4,
                "payMode": 0,
                "productId": 4005461,
                "productVersionId": 86446974,
                "recorderId": 401,
                "specialAuth": 0,
                "updateTime": "2024-08-16T18:01:36.000+0800",
                "updaterId": 401
            }
        ],
        "saMultiple": 1,
        "saSchedualUnit": "1",
        "sectionCalType": "1",
        "selfConfirm": "N",
        "specialDiscnt": "N",
        "spouseProdIndi": "N",
        "spouseWaiver": "N",
        "stampIndicator": "0",
        "stampdutyOption": "0",
        "standAloneRider": "N",
        "standLifeIndi": "N",
        "startDate": "2023-06-01T08:00:00.000+0800",
        "suddenRate": 0,
        "surrChargeIndi": "N",
        "switchFee": 0,
        "switchPeriodUnit": "1",
        "sysLockStatus": "0",
        "tablePrem": "Y",
        "targetType": "0",
        "testProducts": [
            {
                "empty": false,
                "entityId": 86446975,
                "listId": 86446975,
                "productId": 4005461,
                "testTypeId": 0
            }
        ],
        "tmlBonusIndi": "N",
        "tmlBonusIntRate": 0,
        "topupPermit": "N",
        "topupStartYear": 1,
        "underwriteJob": "0",
        "uniqueIdNo": "TERM2",
        "unitFlag": "2",
        "universalPrem": "N",
        "uptoageIndi": "N",
        "uwJet": "N",
        "uwManual": "N",
        "value": "N",
        "waitDaysAfLapse": 0,
        "waiver": "N",
        "waiverBenefit": "N",
        "waiverInterestRate": 0,
        "waiverType": "3"
    },
    "productFormulas": [
        {
            "extendedProps": {},
            "formulaId": "DIPLI_000000001019510",
            "formulaName": "StandardPrem_1YTERM"
        },
        {
            "extendedProps": {},
            "formulaId": "DIPLI_000000001019511",
            "formulaName": "InforceSA_TERM2"
        },
        {
            "extendedProps": {},
            "formulaId": "DIPLI_000000001019512",
            "formulaName": "AN_Formula_byStages"
        }
    ],
    "ratetables": [
        {
            "extendedProps": {},
            "ratetableCode": "RATE_DIPLI_000000001058715",
            "ratetableName": "PremiumRate(1Y_TERM)"
        },
        {
            "extendedProps": {},
            "ratetableCode": "RATE_DIPLI_000000001058716",
            "ratetableName": "ProductUnitRate(TERM2)"
        },
        {
            "extendedProps": {},
            "ratetableCode": "RATE_DIPLI_000000001058717",
            "ratetableName": "ProductCommissionRate(TERM2)"
        },
        {
            "extendedProps": {},
            "ratetableCode": "RATE_DIPLI_000000001030110",
            "ratetableName": "Modal Factor"
        }
    ],
    "result": 1,
    "traceId": "58116e53f3aedc26032901d12254760e"
}